munkres.py
jk_munkres-1.0.0.dist-info/LICENSE.md
jk_munkres-1.0.0.dist-info/METADATA
jk_munkres-1.0.0.dist-info/WHEEL
jk_munkres-1.0.0.dist-info/top_level.txt
jk_munkres-1.0.0.dist-info/RECORD
